aws_spot_advisor_sejto/__init__.py
aws_spot_advisor_sejto/sejto.py
aws_spot_advisor_sejto/lib/__init__.py
aws_spot_advisor_sejto/lib/cli_args.py
aws_spot_advisor_sejto/lib/conf.py
aws_spot_advisor_sejto/lib/dataset.py
aws_spot_advisor_sejto/lib/filters.py
aws_spot_advisor_sejto/lib/formatters.py
aws_spot_advisor_sejto/lib/models.py
aws_spot_advisor_sejto-0.0.3.dist-info/METADATA
aws_spot_advisor_sejto-0.0.3.dist-info/WHEEL
aws_spot_advisor_sejto-0.0.3.dist-info/entry_points.txt
aws_spot_advisor_sejto-0.0.3.dist-info/top_level.txt
aws_spot_advisor_sejto-0.0.3.dist-info/RECORD
