Metadata-Version: 2.4
Name: aws_spot_advisor_sejto
Version: 0.0.3
Summary: Slightly improved version of AWS Spot Advisor
Author: Zdenek Styblik
Project-URL: Repository, https://github.com/zstyblik/aws-spot-advisor-sejto.git
Project-URL: Issues, https://github.com/zstyblik/aws-spot-advisor-sejto/issues
Keywords: aws
Classifier: Environment :: Console
Classifier: Intended Audience :: System Administrators
Classifier: Operating System :: OS Independent
Classifier: Programming Language :: Python :: 3
Requires-Python: >=3.11
Requires-Dist: requests==2.32.4
